{
  "annotations": {
    "list": [
      {
        "builtIn": 1,
        "datasource": {
          "type": "grafana",
          "uid": "-- Grafana --"
        },
        "enable": true,
        "hide": true,
        "iconColor": "rgba(0, 211, 255, 1)",
        "name": "Annotations & Alerts",
        "type": "dashboard"
      }
    ]
  },
  "editable": true,
  "fiscalYearStartMonth": 0,
  "graphTooltip": 0,
  "links": [
    {
      "asDropdown": false,
      "icon": "external link",
      "includeVars": false,
      "keepTime": false,
      "tags": [],
      "targetBlank": false,
      "title": "New link",
      "tooltip": "",
      "type": "link",
      "url": ""
    }
  ],
  "panels": [
    {
      "datasource": {
        "default": true,
        "type": "prometheus",
        "uid": "prometheus"
      },
      "fieldConfig": {
        "defaults": {
          "color": {
            "mode": "thresholds"
          },
          "displayName": "HTTP Response Time",
          "mappings": [],
          "thresholds": {
            "mode": "absolute",
            "steps": [
              {
                "color": "green",
                "value": null
              },
              {
                "color": "#EAB839",
                "value": 0.3
              },
              {
                "color": "red",
                "value": 0.5
              }
            ]
          },
          "unit": "s"
        },
        "overrides": []
      },
      "gridPos": {
        "h": 8,
        "w": 12,
        "x": 0,
        "y": 0
      },
      "id": 12,
      "options": {
        "colorMode": "background",
        "graphMode": "area",
        "justifyMode": "auto",
        "orientation": "auto",
        "percentChangeColorMode": "standard",
        "reduceOptions": {
          "calcs": [
            "lastNotNull"
          ],
          "fields": "",
          "values": false
        },
        "showPercentChange": false,
        "textMode": "auto",
        "wideLayout": true
      },
      "pluginVersion": "11.2.0",
      "targets": [
        {
          "datasource": {
            "type": "prometheus",
            "uid": "prometheus"
          },
          "editorMode": "code",
          "expr": "http_server_requests_seconds_sum{uri=\"/movies/$endpoint\", error=\"none\"}\n/http_server_requests_seconds_count{uri=\"/movies/$endpoint\", error=\"none\"}",
          "instant": false,
          "legendFormat": "{{uri}} response time",
          "range": true,
          "refId": "A"
        }
      ],
      "type": "stat"
    },
    {
      "datasource": {
        "default": true,
        "type": "prometheus",
        "uid": "prometheus"
      },
      "fieldConfig": {
        "defaults": {
          "color": {
            "mode": "thresholds"
          },
          "displayName": "Cache",
          "mappings": [],
          "thresholds": {
            "mode": "absolute",
            "steps": [
              {
                "color": "text",
                "value": null
              }
            ]
          },
          "unit": "reqps"
        },
        "overrides": []
      },
      "gridPos": {
        "h": 8,
        "w": 12,
        "x": 0,
        "y": 8
      },
      "id": 5,
      "options": {
        "colorMode": "value",
        "graphMode": "area",
        "justifyMode": "auto",
        "orientation": "auto",
        "percentChangeColorMode": "standard",
        "reduceOptions": {
          "calcs": [
            "lastNotNull"
          ],
          "fields": "",
          "values": false
        },
        "showPercentChange": false,
        "textMode": "auto",
        "wideLayout": true
      },
      "pluginVersion": "11.2.0",
      "targets": [
        {
          "datasource": {
            "type": "prometheus",
            "uid": "prometheus"
          },
          "editorMode": "code",
          "expr": "rate(cache_gets_total{name=\"$endpoint\", result=\"hit\"}[10s])",
          "instant": false,
          "legendFormat": "__auto",
          "range": true,
          "refId": "A"
        }
      ],
      "type": "stat"
    },
    {
      "datasource": {
        "default": true,
        "type": "prometheus",
        "uid": "prometheus"
      },
      "fieldConfig": {
        "defaults": {
          "color": {
            "mode": "thresholds"
          },
          "displayName": "TMDB API",
          "mappings": [],
          "thresholds": {
            "mode": "absolute",
            "steps": [
              {
                "color": "blue",
                "value": null
              }
            ]
          },
          "unit": "reqps"
        },
        "overrides": []
      },
      "gridPos": {
        "h": 8,
        "w": 12,
        "x": 0,
        "y": 16
      },
      "id": 8,
      "options": {
        "colorMode": "value",
        "graphMode": "area",
        "justifyMode": "auto",
        "orientation": "auto",
        "percentChangeColorMode": "standard",
        "reduceOptions": {
          "calcs": [
            "lastNotNull"
          ],
          "fields": "",
          "values": false
        },
        "showPercentChange": false,
        "textMode": "auto",
        "wideLayout": true
      },
      "pluginVersion": "11.2.0",
      "targets": [
        {
          "datasource": {
            "type": "prometheus",
            "uid": "prometheus"
          },
          "editorMode": "code",
          "expr": "rate(tmdb_api_requests_seconds_count{method=\"$endpoint\"}[10s])",
          "instant": false,
          "legendFormat": "__auto",
          "range": true,
          "refId": "A"
        }
      ],
      "type": "stat"
    },
    {
      "datasource": {
        "default": true,
        "type": "prometheus",
        "uid": "prometheus"
      },
      "fieldConfig": {
        "defaults": {
          "color": {
            "mode": "thresholds"
          },
          "displayName": "Search Response Time",
          "mappings": [],
          "thresholds": {
            "mode": "absolute",
            "steps": [
              {
                "color": "green",
                "value": null
              },
              {
                "color": "#EAB839",
                "value": 0.5
              },
              {
                "color": "red",
                "value": 1
              }
            ]
          },
          "unit": "s"
        },
        "overrides": []
      },
      "gridPos": {
        "h": 8,
        "w": 12,
        "x": 0,
        "y": 24
      },
      "id": 10,
      "options": {
        "colorMode": "background",
        "graphMode": "area",
        "justifyMode": "auto",
        "orientation": "auto",
        "percentChangeColorMode": "standard",
        "reduceOptions": {
          "calcs": [
            "lastNotNull"
          ],
          "fields": "",
          "values": false
        },
        "showPercentChange": false,
        "textMode": "auto",
        "wideLayout": true
      },
      "pluginVersion": "11.2.0",
      "targets": [
        {
          "datasource": {
            "type": "prometheus",
            "uid": "prometheus"
          },
          "editorMode": "code",
          "expr": "redis_requests_seconds_sum{command=\"search\"} / redis_requests_seconds_count{command=\"search\"}",
          "instant": false,
          "legendFormat": "__auto",
          "range": true,
          "refId": "A"
        }
      ],
      "type": "stat"
    }
  ],
  "refresh": "5s",
  "schemaVersion": 39,
  "tags": [],
  "templating": {
    "list": [
      {
        "current": {
          "selected": true,
          "text": "popular",
          "value": "popular"
        },
        "hide": 0,
        "includeAll": false,
        "label": "Endpoint",
        "multi": false,
        "name": "endpoint",
        "options": [
          {
            "selected": true,
            "text": "popular",
            "value": "popular"
          },
          {
            "selected": false,
            "text": "top-rated",
            "value": "top-rated"
          }
        ],
        "query": "popular,top-rated",
        "queryValue": "",
        "skipUrlSync": false,
        "type": "custom"
      }
    ]
  },
  "time": {
    "from": "now-5m",
    "to": "now"
  },
  "timepicker": {},
  "timezone": "browser",
  "title": "Redis Cache Demo",
  "uid": "1",
  "version": 2,
  "weekStart": ""
}